{
  "phase": 22,
  "name": "Meta-Optimization & Autonomous Tuning",
  "status": "implemented",
  "modules": [
    "buddy_phase22_meta_optimizer.py",
    "buddy_phase22_agent_tuner.py",
    "buddy_phase22_scheduler.py",
    "buddy_phase22_feedback_loop.py",
    "buddy_phase22_monitor.py"
  ],
  "harness": "buddy_phase22_harness.py",
  "tests": {
    "file": "buddy_phase22_tests.py",
    "total_tests": 32
  },
  "metrics_targets": {
    "success_rate": 0.90,
    "throughput": 35,
    "agent_utilization": 0.70,
    "confidence_trajectory": 0.95,
    "schedule_adherence": 0.95,
    "system_health": 90,
    "optimization_efficiency": 0.90
  },
  "outputs": [
    "phase22/metrics.jsonl",
    "phase22/anomalies.jsonl",
    "phase22/system_health.json",
    "phase22/learning_signals.jsonl",
    "phase22/meta_optimization_report.md",
    "phase22/wave_X/agent_Y/tuned_parameters.jsonl",
    "phase22/wave_X/agent_Y/adjusted_schedule.jsonl",
    "phase16/phase22_feedback.jsonl",
    "phase18/phase22_feedback.jsonl",
    "phase20/phase22_feedback.jsonl"
  ],
  "reports": [
    "PHASE_22_VERIFICATION_INDEX.md",
    "PHASE_22_COMPLETION_SUMMARY.md",
    "PHASE_22_TECHNICAL_ANALYSIS.md",
    "PHASE_22_OPTIMIZATION_REPORT.md"
  ]
}
